mm_eth/__init__.py
mm_eth/abi.py
mm_eth/account.py
mm_eth/anvil.py
mm_eth/converters.py
mm_eth/deploy.py
mm_eth/erc20.py
mm_eth/py.typed
mm_eth/retry.py
mm_eth/rpc.py
mm_eth/solc.py
mm_eth/tx.py
mm_eth/utils.py
mm_eth/cli/__init__.py
mm_eth/cli/calcs.py
mm_eth/cli/cli.py
mm_eth/cli/cli_utils.py
mm_eth/cli/rpc_helpers.py
mm_eth/cli/validators.py
mm_eth/cli/cmd/__init__.py
mm_eth/cli/cmd/balance_cmd.py
mm_eth/cli/cmd/balances_cmd.py
mm_eth/cli/cmd/deploy_cmd.py
mm_eth/cli/cmd/node_cmd.py
mm_eth/cli/cmd/solc_cmd.py
mm_eth/cli/cmd/transfer_cmd.py
mm_eth/cli/cmd/wallet/__init__.py
mm_eth/cli/cmd/wallet/mnemonic_cmd.py
mm_eth/cli/cmd/wallet/private_key_cmd.py
mm_eth-0.7.2.dist-info/METADATA
mm_eth-0.7.2.dist-info/WHEEL
mm_eth-0.7.2.dist-info/entry_points.txt
mm_eth-0.7.2.dist-info/RECORD
