Metadata-Version: 2.4
Name: mm-eth
Version: 0.7.2
Requires-Python: >=3.13
Requires-Dist: mm-web3~=0.5.2
Requires-Dist: typer~=0.16.1
Requires-Dist: web3~=7.13.0
